{
  "captured_at_utc": "2026-04-26T13:03:46.810827",
  "reference_date": "2026-04-26",
  "cohort_as_of_date": "2026-04-24",
  "events": 20,
  "live_snapshot_path": "logs/snapshots/2026-04-24_polymarket_blind_live_validation.json",
  "cohort_summary": {
    "events": 20,
    "model_mode_hit_rate": 0.4,
    "market_mode_hit_rate": 0.45,
    "model_log_loss": 3.627852327213506,
    "market_log_loss": 1.6566580247422351,
    "model_brier": 0.7536217547578703,
    "market_brier": 0.7800543375,
    "paper_trades": 12,
    "paper_total_stake": 3.766,
    "paper_total_pnl": 2.234,
    "paper_roi_on_stake": 0.5932023366967605
  },
  "by_quality_tier": {
    "A": {
      "events": 18,
      "model_mode_hit_rate": 0.3888888888888889,
      "market_mode_hit_rate": 0.5,
      "model_log_loss": 3.9752274749754566,
      "market_log_loss": 1.5977939887753105,
      "model_brier": 0.8057948672973344,
      "market_brier": 0.7213886111111112,
      "paper_trades": 11,
      "paper_total_stake": 3.386,
      "paper_total_pnl": 1.614,
      "paper_roi_on_stake": 0.47666863555818073
    },
    "B": {
      "events": 1,
      "model_mode_hit_rate": 0.0,
      "market_mode_hit_rate": 0.0,
      "model_log_loss": 0.7957300227902854,
      "market_log_loss": 3.1349943408874985,
      "model_brier": 0.524284520653603,
      "market_brier": 1.8103085,
      "paper_trades": 0,
      "paper_total_stake": 0,
      "paper_total_pnl": 0,
      "paper_roi_on_stake": 0.0
    },
    "C": {
      "events": 1,
      "model_mode_hit_rate": 1.0,
      "market_mode_hit_rate": 0.0,
      "model_log_loss": 0.20722197192161226,
      "market_log_loss": 1.2378743560016172,
      "model_brier": 0.043842963151783584,
      "market_brier": 0.80578325,
      "paper_trades": 1,
      "paper_total_stake": 0.38,
      "paper_total_pnl": 0.62,
      "paper_roi_on_stake": 1.631578947368421
    }
  },
  "by_watchlist_signal": {
    "aligned": {
      "events": 2,
      "model_mode_hit_rate": 1.0,
      "market_mode_hit_rate": 1.0,
      "model_log_loss": 5.551115123125783e-17,
      "market_log_loss": 0.002252566444395778,
      "model_brier": 6.162975822039155e-33,
      "market_brier": 2.562499999999987e-05,
      "paper_trades": 0,
      "paper_total_stake": 0,
      "paper_total_pnl": 0,
      "paper_roi_on_stake": 0.0
    },
    "mixed": {
      "events": 12,
      "model_mode_hit_rate": 0.4166666666666667,
      "market_mode_hit_rate": 0.4166666666666667,
      "model_log_loss": 3.7206709672217806,
      "market_log_loss": 1.7161848671093665,
      "model_brier": 0.7628909176606252,
      "market_brier": 0.7642027916666666,
      "paper_trades": 11,
      "paper_total_stake": 3.6734999999999998,
      "paper_total_pnl": 1.3265000000000002,
      "paper_roi_on_stake": 0.36109976861303944
    },
    "opposed": {
      "events": 5,
      "model_mode_hit_rate": 0.2,
      "market_mode_hit_rate": 0.4,
      "model_log_loss": 5.322942161058684,
      "market_log_loss": 1.960213789511403,
      "model_brier": 1.005679339368077,
      "market_brier": 1.03529955,
      "paper_trades": 0,
      "paper_total_stake": 0,
      "paper_total_pnl": 0,
      "paper_roi_on_stake": 0.0
    },
    "silent": {
      "events": 1,
      "model_mode_hit_rate": 0.0,
      "market_mode_hit_rate": 0.0,
      "model_log_loss": 1.2942841323153296,
      "market_log_loss": 2.7333680090865,
      "model_brier": 0.8893473863895186,
      "market_brier": 1.2541042500000001,
      "paper_trades": 1,
      "paper_total_stake": 0.09250000000000001,
      "paper_total_pnl": 0.9075,
      "paper_roi_on_stake": 9.810810810810809
    }
  },
  "stations": [
    {
      "station_code": "KBKF",
      "event_slug": "highest-temperature-in-denver-on-april-24-2026",
      "top_edge_quality_tier": "A",
      "watchlist_signal": "mixed",
      "paper_trade_taken": true,
      "paper_trade_pnl": -0.5125,
      "model_mode_hit": false,
      "market_mode_hit": false,
      "model_log_loss": 1.222774020974434,
      "market_log_loss": 1.4696759700589417,
      "log_loss_delta_vs_market": -0.2469019490845077,
      "top_edge_question": "Will the highest temperature in Denver be between 70-71°F on April 24?",
      "winner_question": "Will the highest temperature in Denver be between 72-73°F on April 24?"
    },
    {
      "station_code": "UUWW",
      "event_slug": "highest-temperature-in-moscow-on-april-24-2026",
      "top_edge_quality_tier": "A",
      "watchlist_signal": "mixed",
      "paper_trade_taken": true,
      "paper_trade_pnl": -0.44749999999999995,
      "model_mode_hit": false,
      "market_mode_hit": false,
      "model_log_loss": 10.773498005217986,
      "market_log_loss": 3.5578511917075324,
      "log_loss_delta_vs_market": 7.215646813510453,
      "top_edge_question": "Will the highest temperature in Moscow be 6°C on April 24?",
      "winner_question": "Will the highest temperature in Moscow be 4°C on April 24?"
    },
    {
      "station_code": "EFHK",
      "event_slug": "highest-temperature-in-helsinki-on-april-24-2026",
      "top_edge_quality_tier": "A",
      "watchlist_signal": "mixed",
      "paper_trade_taken": true,
      "paper_trade_pnl": -0.2675,
      "model_mode_hit": false,
      "market_mode_hit": true,
      "model_log_loss": 4.1775356273821735,
      "market_log_loss": 0.32158362412746233,
      "log_loss_delta_vs_market": 3.8559520032547114,
      "top_edge_question": "Will the highest temperature in Helsinki be 12°C on April 24?",
      "winner_question": "Will the highest temperature in Helsinki be 11°C on April 24?"
    },
    {
      "station_code": "KMIA",
      "event_slug": "highest-temperature-in-miami-on-april-24-2026",
      "top_edge_quality_tier": "A",
      "watchlist_signal": "mixed",
      "paper_trade_taken": true,
      "paper_trade_pnl": -0.255,
      "model_mode_hit": false,
      "market_mode_hit": true,
      "model_log_loss": 1.0251982924272869,
      "market_log_loss": 0.8209805520698302,
      "log_loss_delta_vs_market": 0.20421774035745666,
      "top_edge_question": "Will the highest temperature in Miami be between 82-83°F on April 24?",
      "winner_question": "Will the highest temperature in Miami be between 80-81°F on April 24?"
    },
    {
      "station_code": "EDDM",
      "event_slug": "highest-temperature-in-munich-on-april-24-2026",
      "top_edge_quality_tier": "A",
      "watchlist_signal": "mixed",
      "paper_trade_taken": true,
      "paper_trade_pnl": -0.225,
      "model_mode_hit": false,
      "market_mode_hit": false,
      "model_log_loss": 5.08165133534873,
      "market_log_loss": 3.4265151896464454,
      "log_loss_delta_vs_market": 1.6551361457022846,
      "top_edge_question": "Will the highest temperature in Munich be 19°C on April 24?",
      "winner_question": "Will the highest temperature in Munich be 18°C on April 24?"
    },
    {
      "station_code": "KORD",
      "event_slug": "highest-temperature-in-chicago-on-april-24-2026",
      "top_edge_quality_tier": "A",
      "watchlist_signal": "mixed",
      "paper_trade_taken": true,
      "paper_trade_pnl": -0.2225,
      "model_mode_hit": false,
      "market_mode_hit": false,
      "model_log_loss": 20.72326583694641,
      "market_log_loss": 2.8302178350764176,
      "log_loss_delta_vs_market": 17.893048001869992,
      "top_edge_question": "Will the highest temperature in Chicago be between 74-75°F on April 24?",
      "winner_question": "Will the highest temperature in Chicago be between 68-69°F on April 24?"
    },
    {
      "station_code": "MPMG",
      "event_slug": "highest-temperature-in-panama-city-on-april-24-2026",
      "top_edge_quality_tier": "B",
      "watchlist_signal": "opposed",
      "paper_trade_taken": false,
      "paper_trade_pnl": 0.0,
      "model_mode_hit": false,
      "market_mode_hit": false,
      "model_log_loss": 0.7957300227902854,
      "market_log_loss": 3.1349943408874985,
      "log_loss_delta_vs_market": -2.339264318097213,
      "top_edge_question": "Will the highest temperature in Panama City be 30°C on April 24?",
      "winner_question": "Will the highest temperature in Panama City be 30°C on April 24?"
    },
    {
      "station_code": "KLAX",
      "event_slug": "highest-temperature-in-los-angeles-on-april-24-2026",
      "top_edge_quality_tier": "A",
      "watchlist_signal": "opposed",
      "paper_trade_taken": false,
      "paper_trade_pnl": 0.0,
      "model_mode_hit": true,
      "market_mode_hit": true,
      "model_log_loss": 0.15644557567811357,
      "market_log_loss": 0.9545119446943529,
      "log_loss_delta_vs_market": -0.7980663690162393,
      "top_edge_question": "Will the highest temperature in Los Angeles be between 72-73°F on April 24?",
      "winner_question": "Will the highest temperature in Los Angeles be between 72-73°F on April 24?"
    },
    {
      "station_code": "SAEZ",
      "event_slug": "highest-temperature-in-buenos-aires-on-april-24-2026",
      "top_edge_quality_tier": "A",
      "watchlist_signal": "opposed",
      "paper_trade_taken": false,
      "paper_trade_pnl": 0.0,
      "model_mode_hit": false,
      "market_mode_hit": false,
      "model_log_loss": 1.585507348660197,
      "market_log_loss": 2.2537949288246137,
      "log_loss_delta_vs_market": -0.6682875801644168,
      "top_edge_question": "Will the highest temperature in Buenos Aires be 23°C on April 24?",
      "winner_question": "Will the highest temperature in Buenos Aires be 22°C on April 24?"
    },
    {
      "station_code": "KAUS",
      "event_slug": "highest-temperature-in-austin-on-april-24-2026",
      "top_edge_quality_tier": "A",
      "watchlist_signal": "mixed",
      "paper_trade_taken": false,
      "paper_trade_pnl": 0.0,
      "model_mode_hit": true,
      "market_mode_hit": true,
      "model_log_loss": -0.0,
      "market_log_loss": 0.004510155477886019,
      "log_loss_delta_vs_market": -0.004510155477886019,
      "top_edge_question": "Will the highest temperature in Austin be 74°F or higher on April 24?",
      "winner_question": "Will the highest temperature in Austin be 74°F or higher on April 24?"
    },
    {
      "station_code": "KHOU",
      "event_slug": "highest-temperature-in-houston-on-april-24-2026",
      "top_edge_quality_tier": "A",
      "watchlist_signal": "aligned",
      "paper_trade_taken": false,
      "paper_trade_pnl": 0.0,
      "model_mode_hit": true,
      "market_mode_hit": true,
      "model_log_loss": -0.0,
      "market_log_loss": 0.002503130218118477,
      "log_loss_delta_vs_market": -0.002503130218118477,
      "top_edge_question": "Will the highest temperature in Houston be 76°F or higher on April 24?",
      "winner_question": "Will the highest temperature in Houston be 76°F or higher on April 24?"
    },
    {
      "station_code": "MMMX",
      "event_slug": "highest-temperature-in-mexico-city-on-april-24-2026",
      "top_edge_quality_tier": "A",
      "watchlist_signal": "aligned",
      "paper_trade_taken": false,
      "paper_trade_pnl": 0.0,
      "model_mode_hit": true,
      "market_mode_hit": true,
      "model_log_loss": 1.1102230246251565e-16,
      "market_log_loss": 0.0020020026706730793,
      "log_loss_delta_vs_market": -0.0020020026706729682,
      "top_edge_question": "Will the highest temperature in Mexico City be 21°C or higher on April 24?",
      "winner_question": "Will the highest temperature in Mexico City be 21°C or higher on April 24?"
    },
    {
      "station_code": "EGLC",
      "event_slug": "highest-temperature-in-london-on-april-24-2026",
      "top_edge_quality_tier": "A",
      "watchlist_signal": "opposed",
      "paper_trade_taken": false,
      "paper_trade_pnl": 0.0,
      "model_mode_hit": false,
      "market_mode_hit": true,
      "model_log_loss": 3.353762021218412,
      "market_log_loss": 0.8675005677047231,
      "log_loss_delta_vs_market": 2.486261453513689,
      "top_edge_question": "Will the highest temperature in London be 17°C on April 24?",
      "winner_question": "Will the highest temperature in London be 18°C on April 24?"
    },
    {
      "station_code": "EHAM",
      "event_slug": "highest-temperature-in-amsterdam-on-april-24-2026",
      "top_edge_quality_tier": "A",
      "watchlist_signal": "opposed",
      "paper_trade_taken": false,
      "paper_trade_pnl": 0.0,
      "model_mode_hit": false,
      "market_mode_hit": false,
      "model_log_loss": 20.72326583694641,
      "market_log_loss": 2.5902671654458262,
      "log_loss_delta_vs_market": 18.132998671500584,
      "top_edge_question": "Will the highest temperature in Amsterdam be 18°C on April 24?",
      "winner_question": "Will the highest temperature in Amsterdam be 14°C on April 24?"
    },
    {
      "station_code": "LEMD",
      "event_slug": "highest-temperature-in-madrid-on-april-24-2026",
      "top_edge_quality_tier": "A",
      "watchlist_signal": "mixed",
      "paper_trade_taken": true,
      "paper_trade_pnl": 0.48250000000000004,
      "model_mode_hit": true,
      "market_mode_hit": true,
      "model_log_loss": 0.30958566684360334,
      "market_log_loss": 0.7444404749474959,
      "log_loss_delta_vs_market": -0.43485480810389254,
      "top_edge_question": "Will the highest temperature in Madrid be 22°C on April 24?",
      "winner_question": "Will the highest temperature in Madrid be 22°C on April 24?"
    },
    {
      "station_code": "KATL",
      "event_slug": "highest-temperature-in-atlanta-on-april-24-2026",
      "top_edge_quality_tier": "A",
      "watchlist_signal": "mixed",
      "paper_trade_taken": true,
      "paper_trade_pnl": 0.5275,
      "model_mode_hit": true,
      "market_mode_hit": true,
      "model_log_loss": 0.11968396366651922,
      "market_log_loss": 0.8096809968158968,
      "log_loss_delta_vs_market": -0.6899970331493775,
      "top_edge_question": "Will the highest temperature in Atlanta be between 82-83°F on April 24?",
      "winner_question": "Will the highest temperature in Atlanta be between 82-83°F on April 24?"
    },
    {
      "station_code": "LTFM",
      "event_slug": "highest-temperature-in-istanbul-on-april-24-2026",
      "top_edge_quality_tier": "C",
      "watchlist_signal": "mixed",
      "paper_trade_taken": true,
      "paper_trade_pnl": 0.62,
      "model_mode_hit": true,
      "market_mode_hit": false,
      "model_log_loss": 0.20722197192161226,
      "market_log_loss": 1.2378743560016172,
      "log_loss_delta_vs_market": -1.030652384080005,
      "top_edge_question": "Will the highest temperature in Istanbul be 17°C on April 24?",
      "winner_question": "Will the highest temperature in Istanbul be 17°C on April 24?"
    },
    {
      "station_code": "KLGA",
      "event_slug": "highest-temperature-in-nyc-on-april-24-2026",
      "top_edge_quality_tier": "A",
      "watchlist_signal": "mixed",
      "paper_trade_taken": true,
      "paper_trade_pnl": 0.665,
      "model_mode_hit": true,
      "market_mode_hit": false,
      "model_log_loss": 0.010711529159680194,
      "market_log_loss": 1.2039728043259361,
      "log_loss_delta_vs_market": -1.193261275166256,
      "top_edge_question": "Will the highest temperature in New York City be 66°F or higher on April 24?",
      "winner_question": "Will the highest temperature in New York City be 66°F or higher on April 24?"
    },
    {
      "station_code": "LTAC",
      "event_slug": "highest-temperature-in-ankara-on-april-24-2026",
      "top_edge_quality_tier": "A",
      "watchlist_signal": "silent",
      "paper_trade_taken": true,
      "paper_trade_pnl": 0.9075,
      "model_mode_hit": false,
      "market_mode_hit": false,
      "model_log_loss": 1.2942841323153296,
      "market_log_loss": 2.7333680090865,
      "log_loss_delta_vs_market": -1.4390838767711704,
      "top_edge_question": "Will the highest temperature in Ankara be 12°C on April 24?",
      "winner_question": "Will the highest temperature in Ankara be 12°C on April 24?"
    },
    {
      "station_code": "LIMC",
      "event_slug": "highest-temperature-in-milan-on-april-24-2026",
      "top_edge_quality_tier": "A",
      "watchlist_signal": "mixed",
      "paper_trade_taken": true,
      "paper_trade_pnl": 0.9615,
      "model_mode_hit": false,
      "market_mode_hit": false,
      "model_log_loss": 0.9969253567729357,
      "market_log_loss": 4.166915255056936,
      "log_loss_delta_vs_market": -3.1699898982840002,
      "top_edge_question": "Will the highest temperature in Milan be 23°C on April 24?",
      "winner_question": "Will the highest temperature in Milan be 23°C on April 24?"
    }
  ],
  "recommendations": {
    "weakest_quality_tiers": [
      {
        "group": "B",
        "events": 1,
        "log_loss_delta_vs_market": -2.339264318097213,
        "paper_total_pnl": 0.0,
        "paper_roi_on_stake": 0.0
      },
      {
        "group": "C",
        "events": 1,
        "log_loss_delta_vs_market": -1.030652384080005,
        "paper_total_pnl": 0.62,
        "paper_roi_on_stake": 1.631578947368421
      },
      {
        "group": "A",
        "events": 18,
        "log_loss_delta_vs_market": 2.377433486200146,
        "paper_total_pnl": 1.614,
        "paper_roi_on_stake": 0.47666863555818073
      }
    ],
    "weakest_watchlist_signals": [
      {
        "group": "aligned",
        "events": 2,
        "log_loss_delta_vs_market": -0.0022525664443957226,
        "paper_total_pnl": 0.0,
        "paper_roi_on_stake": 0.0
      },
      {
        "group": "opposed",
        "events": 5,
        "log_loss_delta_vs_market": 3.362728371547281,
        "paper_total_pnl": 0.0,
        "paper_roi_on_stake": 0.0
      },
      {
        "group": "silent",
        "events": 1,
        "log_loss_delta_vs_market": -1.4390838767711704,
        "paper_total_pnl": 0.9075,
        "paper_roi_on_stake": 9.810810810810809
      },
      {
        "group": "mixed",
        "events": 12,
        "log_loss_delta_vs_market": 2.0044861001124143,
        "paper_total_pnl": 1.3265000000000002,
        "paper_roi_on_stake": 0.36109976861303944
      }
    ],
    "worst_stations_by_pnl": [
      {
        "station_code": "KBKF",
        "event_slug": "highest-temperature-in-denver-on-april-24-2026",
        "top_edge_quality_tier": "A",
        "watchlist_signal": "mixed",
        "paper_trade_taken": true,
        "paper_trade_pnl": -0.5125,
        "model_mode_hit": false,
        "market_mode_hit": false,
        "model_log_loss": 1.222774020974434,
        "market_log_loss": 1.4696759700589417,
        "log_loss_delta_vs_market": -0.2469019490845077,
        "top_edge_question": "Will the highest temperature in Denver be between 70-71°F on April 24?",
        "winner_question": "Will the highest temperature in Denver be between 72-73°F on April 24?"
      },
      {
        "station_code": "UUWW",
        "event_slug": "highest-temperature-in-moscow-on-april-24-2026",
        "top_edge_quality_tier": "A",
        "watchlist_signal": "mixed",
        "paper_trade_taken": true,
        "paper_trade_pnl": -0.44749999999999995,
        "model_mode_hit": false,
        "market_mode_hit": false,
        "model_log_loss": 10.773498005217986,
        "market_log_loss": 3.5578511917075324,
        "log_loss_delta_vs_market": 7.215646813510453,
        "top_edge_question": "Will the highest temperature in Moscow be 6°C on April 24?",
        "winner_question": "Will the highest temperature in Moscow be 4°C on April 24?"
      },
      {
        "station_code": "EFHK",
        "event_slug": "highest-temperature-in-helsinki-on-april-24-2026",
        "top_edge_quality_tier": "A",
        "watchlist_signal": "mixed",
        "paper_trade_taken": true,
        "paper_trade_pnl": -0.2675,
        "model_mode_hit": false,
        "market_mode_hit": true,
        "model_log_loss": 4.1775356273821735,
        "market_log_loss": 0.32158362412746233,
        "log_loss_delta_vs_market": 3.8559520032547114,
        "top_edge_question": "Will the highest temperature in Helsinki be 12°C on April 24?",
        "winner_question": "Will the highest temperature in Helsinki be 11°C on April 24?"
      },
      {
        "station_code": "KMIA",
        "event_slug": "highest-temperature-in-miami-on-april-24-2026",
        "top_edge_quality_tier": "A",
        "watchlist_signal": "mixed",
        "paper_trade_taken": true,
        "paper_trade_pnl": -0.255,
        "model_mode_hit": false,
        "market_mode_hit": true,
        "model_log_loss": 1.0251982924272869,
        "market_log_loss": 0.8209805520698302,
        "log_loss_delta_vs_market": 0.20421774035745666,
        "top_edge_question": "Will the highest temperature in Miami be between 82-83°F on April 24?",
        "winner_question": "Will the highest temperature in Miami be between 80-81°F on April 24?"
      },
      {
        "station_code": "EDDM",
        "event_slug": "highest-temperature-in-munich-on-april-24-2026",
        "top_edge_quality_tier": "A",
        "watchlist_signal": "mixed",
        "paper_trade_taken": true,
        "paper_trade_pnl": -0.225,
        "model_mode_hit": false,
        "market_mode_hit": false,
        "model_log_loss": 5.08165133534873,
        "market_log_loss": 3.4265151896464454,
        "log_loss_delta_vs_market": 1.6551361457022846,
        "top_edge_question": "Will the highest temperature in Munich be 19°C on April 24?",
        "winner_question": "Will the highest temperature in Munich be 18°C on April 24?"
      }
    ]
  }
}